mse_cli_core/__init__.py
mse_cli_core/base64.py
mse_cli_core/bootstrap.py
mse_cli_core/clock_tick.py
mse_cli_core/conf.py
mse_cli_core/enclave.py
mse_cli_core/fs.py
mse_cli_core/ignore_file.py
mse_cli_core/no_sgx_docker.py
mse_cli_core/sgx_docker.py
mse_cli_core/spinner.py
mse_cli_core/test_docker.py
mse_cli_core-0.1a13.dist-info/METADATA
mse_cli_core-0.1a13.dist-info/WHEEL
mse_cli_core-0.1a13.dist-info/top_level.txt
mse_cli_core-0.1a13.dist-info/zip-safe
mse_cli_core-0.1a13.dist-info/RECORD
