Metadata-Version: 2.1
Name: mse-cli-core
Version: 0.1a13
Summary: Utils for MicroService Encryption Python CLIs
Home-page: https://cosmian.com
Author: Cosmian Tech
Author-email: tech@cosmian.com
License: MIT
Project-URL: Documentation, https://docs.cosmian.com
Project-URL: Source, https://github.com/Cosmian/mse-cli-core
Classifier: Development Status :: 5 - Production/Stable
Classifier: Environment :: Console
Classifier: License :: OSI Approved :: MIT License
Classifier: Programming Language :: Python :: 3.8
Classifier: Programming Language :: Python :: 3.9
Requires-Python: >=3.8.0
Requires-Dist: cryptography (<42.0.0,>=41.0.1)
Requires-Dist: docker (<7.0.0,>=6.0.1)
Requires-Dist: intel-sgx-ra (==2.0a14)
Requires-Dist: pydantic (<2.0.0,>=1.10.2)
Requires-Dist: requests (<3.0.0,>=2.31.0)
Requires-Dist: toml (<0.11.0,>=0.10.2)
